{
  "nombre": "Cristal Ramirez Escobar",
  "universidad": "Instituto Tecnologico de Culiacan",
  "ciudad": "Ciudad: culiacan, sinaloa",
  "departamento": "Departamento/Facultad: Economico",
  "calidad_general": 6.0,
  "porcentaje_recomienda": 50,
  "nivel_dificultad": 4.0,
  "etiquetas": [
    "BARCO (2)"
  ],
  "numero_calificaciones": 2,
  "calificaciones": [
    {
      "fecha": "28/Dic/2017",
      "tipo_calificacion": "BUENO",
      "puntaje_calidad_general": 10.0,
      "puntaje_facilidad": 0.0,
      "materia": "---",
      "asistencia": "Obligatoria",
      "calificacion_recibida": "N/A",
      "interes_clase": "",
      "comentario": "[Comentario esperando revisión]",
      "etiquetas_comentario": [
        "Barco"
      ],
      "votos_utiles": "0",
      "votos_no_utiles": "0"
    },
    {
      "fecha": "12/Nov/2017",
      "tipo_calificacion": "MALO",
      "puntaje_calidad_general": 2.0,
      "puntaje_facilidad": 0.0,
      "materia": "---",
      "asistencia": "Obligatoria",
      "calificacion_recibida": "10",
      "interes_clase": "",
      "comentario": "[Comentario esperando revisión]",
      "etiquetas_comentario": [
        "Barco"
      ],
      "votos_utiles": "0",
      "votos_no_utiles": "0"
    }
  ]
}