{
  "nombre": "Edgar Cervantes López",
  "universidad": "Instituto Tecnologico de Culiacan",
  "ciudad": "Ciudad: culiacan, sinaloa",
  "departamento": "Departamento/Facultad: Ing. en Sistemas",
  "calidad_general": 7.1,
  "porcentaje_recomienda": 67,
  "nivel_dificultad": 5.5,
  "etiquetas": [
    "DA BUENA RETROALIMENTACIÓN (1)",
    "RESPETADO POR LOS ESTUDIANTES (1)",
    "LAS CLASES SON LARGAS (4)",
    "CALIFICA DURO (2)",
    "LOS EXÁMENES SON DIFÍCILES (1)",
    "BRINDA APOYO (1)",
    "CLASES EXCELENTES (2)",
    "TOMARÍA SU CLASE OTRA VEZ (2)",
    "POCOS EXÁMENES (1)",
    "INSPIRACIONAL (1)"
  ],
  "numero_calificaciones": 12,
  "calificaciones": [
    {
      "fecha": "14/Ago/2019",
      "tipo_calificacion": "BUENO",
      "puntaje_calidad_general": 10.0,
      "puntaje_facilidad": 0.0,
      "materia": "Programacion de sistemas",
      "asistencia": "Obligatoria",
      "calificacion_recibida": "8",
      "interes_clase": "",
      "comentario": "Un excelente profesor, que se ve que domina los temas y explica de sobras con palitos y manzanas, eso si. Hay que poner atencion todos los dias para no solo escuchar lo que dice si no asimilar la información. Aqui es cuestion de uno si desea o no aprender realmente",
      "etiquetas_comentario": [
        "Inspiracional",
        "Clases excelentes",
        "Tomaría su clase otra vez"
      ],
      "votos_utiles": "1",
      "votos_no_utiles": "0"
    },
    {
      "fecha": "08/May/2018",
      "tipo_calificacion": "MALO",
      "puntaje_calidad_general": 2.0,
      "puntaje_facilidad": 0.0,
      "materia": "Cualquier materia que de",
      "asistencia": "No obligatoria",
      "calificacion_recibida": "N/A",
      "interes_clase": "",
      "comentario": "Rip Edgar Cervantes fue un placer tenerte se profesor pero te corrieron",
      "etiquetas_comentario": [
        "Califica Duro",
        "Las clases son largas",
        "Pocos Exámenes"
      ],
      "votos_utiles": "1",
      "votos_no_utiles": "0"
    },
    {
      "fecha": "23/Mar/2018",
      "tipo_calificacion": "REGULAR",
      "puntaje_calidad_general": 4.0,
      "puntaje_facilidad": 0.0,
      "materia": "Cultura Empresarial",
      "asistencia": "No obligatoria",
      "calificacion_recibida": "N/A",
      "interes_clase": "",
      "comentario": "No hace exámenes no toma asistencia y al final te reprueba aunque le entregues el único trabajo que pide. Ah y también sales 10 minutos después de que termina la hora",
      "etiquetas_comentario": [
        "Las clases son largas"
      ],
      "votos_utiles": "0",
      "votos_no_utiles": "0"
    },
    {
      "fecha": "05/Ago/2017",
      "tipo_calificacion": "BUENO",
      "puntaje_calidad_general": 9.0,
      "puntaje_facilidad": 0.0,
      "materia": "Taller de Sistemas Operativos",
      "asistencia": "No obligatoria",
      "calificacion_recibida": "9.5",
      "interes_clase": "",
      "comentario": "El profesor sabe mucho de la materia y todo lo que le preguntes lo va a explicar de muy buena manera y lo mas claro que le sea posible. Muy buen maestro, no toma asistencia pero sabe quienes van y las ganas que le ponen a su clase.",
      "etiquetas_comentario": [
        "Brinda apoyo",
        "Clases excelentes",
        "Tomaría su clase otra vez"
      ],
      "votos_utiles": "0",
      "votos_no_utiles": "0"
    },
    {
      "fecha": "11/Ene/2017",
      "tipo_calificacion": "BUENO",
      "puntaje_calidad_general": 9.0,
      "puntaje_facilidad": 0.0,
      "materia": "Matematicas Discretas",
      "asistencia": "No obligatoria",
      "calificacion_recibida": "25",
      "interes_clase": "",
      "comentario": "Muy buen profesor, con mucho conocimiento, explica bien, no toma asistencia, no deja tareas ni trabajos, solo da clases, deja todos los hasta ultimo dia del semestre, hace reprobacion grupal. no ayuda",
      "etiquetas_comentario": [
        "Califica Duro",
        "Las clases son largas",
        "Los exámenes son difíciles"
      ],
      "votos_utiles": "1",
      "votos_no_utiles": "0"
    },
    {
      "fecha": "22/Ago/2015",
      "tipo_calificacion": "BUENO",
      "puntaje_calidad_general": 9.0,
      "puntaje_facilidad": 0.0,
      "materia": "admon de redes",
      "asistencia": "No obligatoria",
      "calificacion_recibida": "8.5",
      "interes_clase": "",
      "comentario": "sin comentarios",
      "etiquetas_comentario": [
        "Da buena retroalimentación",
        "Respetado por los estudiantes",
        "Las clases son largas"
      ],
      "votos_utiles": "0",
      "votos_no_utiles": "0"
    },
    {
      "fecha": "27/Abr/2013",
      "tipo_calificacion": "BUENO",
      "puntaje_calidad_general": 10.0,
      "puntaje_facilidad": 0.0,
      "materia": "Programación de sistemas",
      "asistencia": "",
      "calificacion_recibida": "9",
      "interes_clase": "9",
      "comentario": "El mejor profesor que he tuve en ingeniería.\nSu dominio de los temas es simplemente espectacular. \nPara aprobar con él todo depende de que tan interesado estes en aprobar. \n\nSi eres curioso y le preguntas el siempre estará dispuesto a explicarte y apoyarte.\n\nDefinitivamente un docente a seguir",
      "etiquetas_comentario": [],
      "votos_utiles": "1",
      "votos_no_utiles": "0"
    },
    {
      "fecha": "16/Ene/2013",
      "tipo_calificacion": "BUENO",
      "puntaje_calidad_general": 9.0,
      "puntaje_facilidad": 0.0,
      "materia": "Funamentos De Telecomunicaciones",
      "asistencia": "",
      "calificacion_recibida": "10",
      "interes_clase": "10",
      "comentario": "Excelente profesor, si quieres aprender mucho, carga con el, los examenes son abiertos y un poco largos pero explica con peras y manzanas y bastanes cosas.",
      "etiquetas_comentario": [],
      "votos_utiles": "0",
      "votos_no_utiles": "0"
    },
    {
      "fecha": "08/Nov/2012",
      "tipo_calificacion": "MALO",
      "puntaje_calidad_general": 2.0,
      "puntaje_facilidad": 0.0,
      "materia": "---",
      "asistencia": "",
      "calificacion_recibida": "N/A",
      "interes_clase": "N/A",
      "comentario": "[Comentario esperando revisión]",
      "etiquetas_comentario": [],
      "votos_utiles": "0",
      "votos_no_utiles": "0"
    },
    {
      "fecha": "06/Sep/2012",
      "tipo_calificacion": "BUENO",
      "puntaje_calidad_general": 10.0,
      "puntaje_facilidad": 0.0,
      "materia": "Fund. de Telecomunicaciones",
      "asistencia": "",
      "calificacion_recibida": "10",
      "interes_clase": "10",
      "comentario": "Es un excelente profesor explica todo a detalle.",
      "etiquetas_comentario": [],
      "votos_utiles": "0",
      "votos_no_utiles": "0"
    },
    {
      "fecha": "14/Ago/2012",
      "tipo_calificacion": "REGULAR",
      "puntaje_calidad_general": 4.0,
      "puntaje_facilidad": 0.0,
      "materia": "Lenguaje Ensamblador",
      "asistencia": "",
      "calificacion_recibida": "9",
      "interes_clase": "9",
      "comentario": "Es un buen maestro, te explica con \"peras y manzanas\", lo que depende es tu nivel de aprendizaje, si quieres aprender, ponle mucha atencion, es un gran maestro.",
      "etiquetas_comentario": [],
      "votos_utiles": "0",
      "votos_no_utiles": "0"
    },
    {
      "fecha": "14/Ago/2012",
      "tipo_calificacion": "BUENO",
      "puntaje_calidad_general": 7.0,
      "puntaje_facilidad": 0.0,
      "materia": "Lenguaje Ensamblador",
      "asistencia": "",
      "calificacion_recibida": "9",
      "interes_clase": "9",
      "comentario": "Es un profesor con mucho conocimiento, pero al trasmitirlo a los alumnos se le dificulta ya que tal ves piensa que uno ya conoce todo lo que esta explicando, y eso hace que algunas veces todos los alumnos no comprendan lo que se explica",
      "etiquetas_comentario": [],
      "votos_utiles": "0",
      "votos_no_utiles": "0"
    }
  ]
}